client/__init__.py
client/test.py
client/ucnp_start
client/client_log/__init__.py
client/client_log/logging.py
client/img/close.png
client/img/gouxuan.png
client/img/input_background.png
client/img/login_universal_copy_paste_tools.png
client/img/max.png
client/img/min.png
client/img/reg_registeruser.png
client/img/skybility_logo.png
client/img/task_bar.png
client/pywx/WxContext.py
client/pywx/__init__.py
client/pywx/login_gui.py
client/uri/__init__.py
client/uri/connection.py
client/uri/loop.py
client/uri/os_property.py
client/uri/uri.py
ucnp_skybility-2.0.7.data/scripts/ucnp_start
ucnp_skybility-2.0.7.dist-info/LICENSE
ucnp_skybility-2.0.7.dist-info/METADATA
ucnp_skybility-2.0.7.dist-info/WHEEL
ucnp_skybility-2.0.7.dist-info/top_level.txt
ucnp_skybility-2.0.7.dist-info/RECORD
