Metadata-Version: 2.1
Name: ucnp-skybility
Version: 2.0.7
Summary: this is a client to ucnp server for linux platform only
Home-page: https://gitlab.skybilityha.com/experiments/ucnp
Author: skybility ha team
Author-email: support@skybilityha.com
License: UNKNOWN
Platform: UNKNOWN
Classifier: Programming Language :: Python
Classifier: License :: OSI Approved :: MIT License
Classifier: Operating System :: POSIX :: Linux
Requires-Python: >=3.5
Requires-Dist: pyperclip (==1.8.0)
Requires-Dist: python-engineio (==3.13.2)
Requires-Dist: python-socketio (==4.6.0)
Requires-Dist: requests (==2.24.0)
Requires-Dist: wxPython (>=4.0.3)
Requires-Dist: pypubsub (==4.0.3)
Requires-Dist: pinyin (==0.4.0)
Requires-Dist: psutil (==5.5.0)
